{
  "lessonId": "particle-na-softener",
  "stage": "B2.2",
  "lessonTitle": "Softening with นะ",
  "rows": [
    {
      "thai": "รอสักครู่นะ",
      "english": "Wait a moment, okay?"
    },
    {
      "thai": "ช่วยปิดประตูให้หน่อยนะ",
      "english": "Please close the door for me, okay?"
    },
    {
      "thai": "พรุ่งนี้อย่าลืมโทรหาฉันนะ",
      "english": "Don't forget to call me tomorrow, okay?"
    },
    {
      "thai": "ถึงแล้วส่งข้อความมานะ",
      "english": "Message me when you arrive, okay?"
    },
    {
      "thai": "ใจเย็นๆ นะ",
      "english": "Stay calm, okay?"
    },
    {
      "thai": "นั่งตรงนี้ก่อนนะ",
      "english": "Sit here first, okay?"
    },
    {
      "thai": "เรื่องนี้เก็บไว้ก่อนนะ",
      "english": "Let's set this aside first, okay?"
    },
    {
      "thai": "ถ้ามีอะไรโทรมาได้นะ",
      "english": "Call me if anything comes up, okay?"
    },
    {
      "thai": "ลองอ่านย่อหน้านี้อีกทีนะ",
      "english": "Read this paragraph again, okay?"
    },
    {
      "thai": "วันนี้กลับเร็วๆ นะ",
      "english": "Go home early today, okay?"
    },
    {
      "thai": "เอาเอกสารชุดนี้ไปด้วยนะ",
      "english": "Take this set of documents with you, okay?"
    },
    {
      "thai": "ตอนประชุมช่วยฟังให้จบนะ",
      "english": "Please listen until the end during the meeting, okay?"
    },
    {
      "thai": "ขับรถดีๆ นะ",
      "english": "Drive carefully, okay?"
    },
    {
      "thai": "ถ้าไม่เข้าใจถามได้เลยนะ",
      "english": "If you don't understand, just ask, okay?"
    },
    {
      "thai": "อย่าเพิ่งบอกใครนะ",
      "english": "Don't tell anyone yet, okay?"
    },
    {
      "thai": "นัดครั้งหน้าเป็นวันศุกร์นะ",
      "english": "Let's make the next appointment on Friday, okay?"
    },
    {
      "thai": "ฝากปิดไฟด้วยนะ",
      "english": "Please turn off the light too, okay?"
    },
    {
      "thai": "คิดอีกทีก็ได้นะ",
      "english": "You can think about it again, okay?"
    },
    {
      "thai": "เดี๋ยวฉันช่วยดูให้นะ",
      "english": "I'll help take a look, okay?"
    },
    {
      "thai": "ครั้งหน้าเตรียมข้อมูลมาให้ครบหน่อยนะ",
      "english": "Please bring complete information next time, okay?"
    },
    {
      "thai": "พักก่อนก็ได้นะ",
      "english": "You can rest first, okay?"
    },
    {
      "thai": "ถ้าถึงบ้านแล้วบอกฉันนะ",
      "english": "Let me know when you get home, okay?"
    },
    {
      "thai": "เอาแบบเดิมนะ",
      "english": "Let's go with the usual one, okay?"
    },
    {
      "thai": "ลองคุยกับเขาตรงๆ ดูนะ",
      "english": "Try talking to him directly, okay?"
    },
    {
      "thai": "วันนี้อากาศเย็นใส่เสื้อด้วยนะ",
      "english": "It's cool today, so wear a shirt too, okay?"
    }
  ]
}
